{"name":"build-javascript","namedChunkGroups":{"polyfill":{"name":"polyfill","assets":[{"name":"webpack-runtime-fbbd224a7dc18881f24e.js","size":4522},{"name":"polyfill-92cf1e7008015d69f830.js","size":101229}],"filteredAssets":0,"assetsSize":105751,"filteredAuxiliaryAssets":2,"auxiliaryAssetsSize":301648},"app":{"name":"app","assets":[{"name":"webpack-runtime-fbbd224a7dc18881f24e.js","size":4522},{"name":"styles.979967621f927faef567.css","size":40227},{"name":"framework-951361d10e6238821607.js","size":22327},{"name":"app-bfbbb34c15c6bc8fe848.js","size":56748}],"filteredAssets":0,"assetsSize":123824,"filteredAuxiliaryAssets":57,"auxiliaryAssetsSize":7875688},"component---src-pages-404-tsx":{"name":"component---src-pages-404-tsx","assets":[{"name":"styles.979967621f927faef567.css","size":40227},{"name":"commons-239e8b59551decc3f74d.js","size":27801},{"name":"a3336d3c033a5ec9d59a088cb032c68b95c64a61-ec2ca538e79dfc00e7c3.js","size":30581},{"name":"component---src-pages-404-tsx-37173dfdd0c4f53612c3.js","size":636}],"filteredAssets":0,"assetsSize":99245,"filteredAuxiliaryAssets":57,"auxiliaryAssetsSize":7825231},"component---src-pages-index-tsx":{"name":"component---src-pages-index-tsx","assets":[{"name":"styles.979967621f927faef567.css","size":40227},{"name":"commons-239e8b59551decc3f74d.js","size":27801},{"name":"a3336d3c033a5ec9d59a088cb032c68b95c64a61-ec2ca538e79dfc00e7c3.js","size":30581},{"name":"component---src-pages-index-tsx-eadb614950afaa7aead5.js","size":2393}],"filteredAssets":0,"assetsSize":101002,"filteredAuxiliaryAssets":57,"auxiliaryAssetsSize":7831896},"component---src-templates-cv-regular-index-tsx":{"name":"component---src-templates-cv-regular-index-tsx","assets":[{"name":"styles.979967621f927faef567.css","size":40227},{"name":"commons-239e8b59551decc3f74d.js","size":27801},{"name":"component---src-templates-cv-regular-index-tsx-cee239df9a6a26df184d.js","size":32969}],"filteredAssets":0,"assetsSize":100997,"filteredAuxiliaryAssets":56,"auxiliaryAssetsSize":7806160}},"assetsByChunkName":{"polyfill":["webpack-runtime-fbbd224a7dc18881f24e.js","polyfill-92cf1e7008015d69f830.js"],"app":["webpack-runtime-fbbd224a7dc18881f24e.js","styles.979967621f927faef567.css","framework-951361d10e6238821607.js","app-bfbbb34c15c6bc8fe848.js"],"component---src-pages-404-tsx":["styles.979967621f927faef567.css","commons-239e8b59551decc3f74d.js","a3336d3c033a5ec9d59a088cb032c68b95c64a61-ec2ca538e79dfc00e7c3.js","component---src-pages-404-tsx-37173dfdd0c4f53612c3.js"],"component---src-pages-index-tsx":["styles.979967621f927faef567.css","commons-239e8b59551decc3f74d.js","a3336d3c033a5ec9d59a088cb032c68b95c64a61-ec2ca538e79dfc00e7c3.js","component---src-pages-index-tsx-eadb614950afaa7aead5.js"],"component---src-templates-cv-regular-index-tsx":["styles.979967621f927faef567.css","commons-239e8b59551decc3f74d.js","component---src-templates-cv-regular-index-tsx-cee239df9a6a26df184d.js"]},"childAssetsByChunkName":{}}